chitchat_dataset/__init__.py
chitchat_dataset/dataset.json
chitchat_dataset/test_dataset.py
chitchat_dataset-0.9.0.dist-info/LICENSE
chitchat_dataset-0.9.0.dist-info/WHEEL
chitchat_dataset-0.9.0.dist-info/METADATA
chitchat_dataset-0.9.0.dist-info/RECORD
