Metadata-Version: 2.1
Name: chitchat-dataset
Version: 0.9.0
Summary: Open-domain conversational dataset from the BYU PCC lab
Home-page: https://github.com/BYU-PCCL/chitchat-dataset
License: MIT
Keywords: dataset,science,machine learning,conversation
Author: William Myers
Author-email: mwilliammyers@gmail.com
Requires-Python: >=3.6,<4.0
Classifier: License :: OSI Approved :: MIT License
Classifier: Programming Language :: Python :: 3
Classifier: Programming Language :: Python :: 3.6
Classifier: Programming Language :: Python :: 3.7
Classifier: Programming Language :: Python :: 3.8
Project-URL: Repository, https://github.com/BYU-PCCL/chitchat-dataset
